disk_tree/__init__.py
disk_tree/cache.py
disk_tree/config.py
disk_tree/db.py
disk_tree/main.py
disk_tree/model.py
disk_tree/s3.py
disk_tree-0.0.2.dist-info/METADATA
disk_tree-0.0.2.dist-info/WHEEL
disk_tree-0.0.2.dist-info/entry_points.txt
disk_tree-0.0.2.dist-info/top_level.txt
disk_tree-0.0.2.dist-info/RECORD
