Metadata-Version: 2.1
Name: disk-tree
Version: 0.0.2
Summary: Disk/Cloud space usage analyzer
Author: Ryan Williams
Author-email: ryan@runsascoded.com
License: Apache License 2.0
Requires-Dist: click
Requires-Dist: flask
Requires-Dist: flask-sqlalchemy
Requires-Dist: humanize
Requires-Dist: kaleido
Requires-Dist: pandas
Requires-Dist: plotly
Requires-Dist: sqlalchemy <2
Requires-Dist: utz
